[
  {
    "date": "2022-02-13",
    "version": "0.07",
    "changes": [
      {
        "type": "update",
        "name": "Update documentation",
        "github": {
          "issue": 96,
          "pull_request": 105
        }
      },
      {
        "type": "feature",
        "name": "Implement Venus::Match#data",
        "github": {
          "issue": 97,
          "pull_request": 104
        }
      },
      {
        "type": "feature",
        "name": "Implement Venus::Match#expr",
        "github": {
          "issue": 98,
          "pull_request": 103
        }
      },
      {
        "type": "feature",
        "name": "Extend Venus::Role::Coercion with new abilities",
        "github": {
          "issue": 99,
          "pull_request": 102
        }
      },
      {
        "type": "defect",
        "name": "Fix Venus::Class attribute declaration issue",
        "github": {
          "issue": 100,
          "pull_request": 101
        }
      }
    ]
  },
  {
    "date": "2022-02-12",
    "version": "0.06",
    "changes": [
      {
        "type": "feature",
        "name": "Implement Venus::Process",
        "github": {
          "issue": 79,
          "pull_request": 89
        }
      },
      {
        "type": "defect",
        "name": "Fix Venus::Path#mkdirs empty rootdir issue",
        "github": {
          "issue": 90,
          "pull_request": 91
        }
      }
    ]
  },
  {
    "date": "2022-02-04",
    "version": "0.04",
    "changes": [
      {
        "type": "feature",
        "name": "Implement Venus::Role::Matchable",
        "github": {
          "issue": 80,
          "pull_request": 85
        }
      },
      {
        "type": "update",
        "name": "Address CPAN Testers reports",
        "github": {
          "issue": 82,
          "pull_request": 83
        }
      }
    ]
  },
  {
    "date": "2022-02-01",
    "version": "0.03",
    "changes": [
      {
        "type": "feature",
        "name": "Implement Venus::Match",
        "github": {
          "issue": 7,
          "pull_request": 75
        }
      },
      {
        "type": "update",
        "name": "Address CPAN Testers reports",
        "github": {
          "issue": 69,
          "pull_request": 70
        }
      }
    ]
  },
  {
    "date": "2022-01-30",
    "version": "0.02",
    "changes": [
      {
        "type": "update",
        "name": "Update String#render token syntax",
        "github": {
          "issue": 58,
          "pull_request": 60
        }
      },
      {
        "type": "feature",
        "name": "Implement Venus::Template",
        "github": {
          "issue": 56,
          "pull_request": 59
        }
      },
      {
        "type": "feature",
        "name": "Implement Venus::Role::Coercible",
        "github": {
          "issue": 8,
          "pull_request": 51
        }
      },
      {
        "type": "update",
        "name": "Document all proxyable methods",
        "github": {
          "issue": 27,
          "pull_request": 50
        }
      },
      {
        "type": "feature",
        "name": "Implement String#substr",
        "github": {
          "issue": 42,
          "pull_request": 49
        }
      },
      {
        "type": "feature",
        "name": "Implement String#append_with,prepend_with",
        "github": {
          "issue": 47,
          "pull_request": 48
        }
      },
      {
        "type": "feature",
        "name": "Implement String#repeat",
        "github": {
          "issue": 43,
          "pull_request": 46
        }
      },
      {
        "type": "feature",
        "name": "Implement String#prepend",
        "github": {
          "issue": 41,
          "pull_request": 45
        }
      },
      {
        "type": "feature",
        "name": "Implement Venus::Role::Digestable",
        "github": {
          "issue": 3,
          "pull_request": 44
        }
      },
      {
        "type": "update",
        "name": "Require Perl version 5.18+",
        "github": {
          "issue": 29,
          "pull_request": 33
        }
      },
      {
        "type": "defect",
        "name": "Fix Dumpable method calls in list context",
        "github": {
          "issue": 23,
          "pull_request": 24
        }
      },
      {
        "type": "update",
        "name": "Minor refactors to source, documentation, and automation",
        "github": {
          "issue": 10,
          "pull_request": 20
        }
      },
      {
        "type": "update",
        "name": "Document overrides in Venus::Boolean",
        "github": {
          "issue": 14,
          "pull_request": 19
        }
      },
      {
        "type": "update",
        "name": "Update Venus::Json to use encoder/decoder callbacks",
        "github": {
          "issue": 17,
          "pull_request": 18
        }
      },
      {
        "type": "feature",
        "name": "Support any YAML library, deduce booleans",
        "github": {
          "issue": 2,
          "pull_request": 16
        }
      },
      {
        "type": "feature",
        "name": "Support any JSON library via encode/decode callbacks",
        "github": {
          "issue": 1,
          "pull_request": 15
        }
      },
      {
        "type": "update",
        "name": "Document overrides, i.e. overloaded operators",
        "github": {
          "issue": 4,
          "pull_request": 13
        }
      },
      {
        "type": "update",
        "name": "Update CONTRIBUTING.md",
        "github": {
          "issue": 5,
          "pull_request": 12
        }
      },
      {
        "type": "update",
        "name": "JSON::PP support requires 4.00",
        "github": {
          "issue": 9,
          "pull_request": 11
        }
      }
    ]
  }
]
